lockorator/__init__.py
lockorator/asyncio.py
lockorator/exceptions.py
lockorator/redis.py
lockorator-0.1.dist-info/LICENSE
lockorator-0.1.dist-info/METADATA
lockorator-0.1.dist-info/WHEEL
lockorator-0.1.dist-info/top_level.txt
lockorator-0.1.dist-info/RECORD
